full_adder2.v
module half_adder(A, B, C, S);
input A, B;
output C, S;
xor x1(S, A, B);
and x2(C, A, B);
endmodule

module full_adder(A, B, Cin, Cout, S);
input A, B, Cin;
output Cout, S;
inout c1, c2, c3;

half_adder ha1(A, B, c1, c2);
half_adder ha2(c2, Cin, c3, S);
or a1(Cout, c1, c3);
endmodule

full_adder_tb.v
`timescale 10ns/10ps
module tb;
  reg A, B, Cin;
  wire Cout, S;
  full_adder dut(A, B, Cin, Cout, S);
  initial begin
    $monitor("A = %b, B = %b, Cin = %b, Cout = %b, S = %b", A, B, Cin, Cout, S);
    $dumpfile("dump.vcd");
    $dumpvars(0, A, B, Cin, Cout, S);
    A= 0; B= 0; Cin= 0; 
    #5 A= 0; B= 1; Cin= 0; 
    #5 A= 1; B= 0; Cin= 0; 
    #5 A= 1; B= 1; Cin= 0; 
    #5 A= 0; B= 0; Cin= 1; 
    #5 A= 0; B= 1; Cin= 1; 
    #5 A= 1; B= 0; Cin= 1; 
    #5 A= 1; B= 1; Cin= 1; 
  end
endmodule

dump.vcd
$date
	Fri Mar 15 09:55:04 2024
$end
$version
	Icarus Verilog
$end
$timescale
	10ps
$end
$scope module tb $end
$var reg 1 ! A $end
$upscope $end
$scope module tb $end
$var reg 1 " B $end
$upscope $end
$scope module tb $end
$var reg 1 # Cin $end
$upscope $end
$scope module tb $end
$var wire 1 $ Cout $end
$upscope $end
$scope module tb $end
$var wire 1 % S $end
$upscope $end
$enddefinitions $end
#0
$dumpvars
0%
0$
0#
0"
0!
$end
#5000
1%
1"
#10000
0"
1!
#15000
0%
1$
1"
#20000
0$
1%
1#
0"
0!
#25000
1$
0%
1"
#30000
0"
1!
#35000
1%
1"
