mealy_non.v
module mealy_non_101(in, out , R, clk);
input in;
input R;
input clk;
output reg out;
parameter [1:0] S0 = 2'b00;
parameter [1:0] S1 = 2'b01;
parameter [1:0] S2 = 2'b10;

localparam logic [1:0] S0_val = S0;
localparam logic [1:0] S1_val = S1;
localparam logic [1:0] S2_val = S2;

logic [1:0] state;

always @(posedge clk or posedge R) begin
        if (R) begin
                out <= 1'b0;
                state <= S0;
        end
        else begin
                case(state)
                        S0: begin
                                if (in)
				begin
                                        state <= S1;
					out <= 1'b0;
				end
				else
					out <= 1'b0;
                        end
                        S1: begin
                                if (~in)
				begin
                                        state <=S2;
                                	out <= 1'b0;
				end
                        end
                        S2: begin
                                if (in)
                                begin
                                        state <= S0;
                                        out <= 1'b1;
                                end
                                else
                                begin
                                        state <= S0;
                                        out <= 1'b0;
                                end
                        end
                endcase
        end
end
endmodule

mealy_non_tb.v
`timescale 10ns/1ps
module tb;
    localparam CLK_PERIOD = 10;
    localparam SIM_DURATION = 100;

    reg clk = 0; 
    reg in = 0; 
    reg R = 1; 
    wire out; 

    mealy_non_101 dut (
        .clk(clk),
        .in(in),
        .R(R),
        .out(out)
    );

    always #((CLK_PERIOD / 2)) clk = ~clk;

    initial begin
	$monitor("in = %b, out = %b", in, out);
	$dumpfile("mealy_non.vcd");
	$dumpvars(0, in, out, clk, R);
        R = 1;
        in = 0;
        #10;
        R = 0;
        #5 in = 1;
        #5 in = 0;
        #5 in = 1;
        #5 in = 1;
        #5 in = 0;
        #5 in = 1;
        #SIM_DURATION;
        $finish;
    end

endmodule

moore_non.vcd
$date
	Mon Mar 18 08:26:15 2024
$end
$version
	Icarus Verilog
$end
$timescale
	1ps
$end
$scope module tb $end
$var reg 1 ! in $end
$upscope $end
$scope module tb $end
$var wire 1 " out $end
$upscope $end
$scope module tb $end
$var reg 1 # clk $end
$upscope $end
$scope module tb $end
$var reg 1 $ R $end
$upscope $end
$enddefinitions $end
#0
$dumpvars
1$
0#
0"
0!
$end
#50000
1#
#100000
0#
0$
#150000
1#
1!
#200000
0#
0!
#250000
1#
1!
#300000
0#
#350000
1#
0!
#400000
0#
1!
#450000
1"
1#
#500000
0#
#550000
0"
1#
