priority.v
module priority_encoder(D, Q);
parameter N = 4;
input [2**N-1:0] D;
output reg [N-1:0] Q;
integer i;
always @(*) begin
	Q[N-1:0] = 'bx;
	for(i = 0; i < 2**N; i = i+1)
	begin
		if (D[i])
		begin
			Q[N-1:0] = 0;
			Q = i;
		end
	end
end
endmodule

priority_tb.v
`timescale 10ns/1ps
module tb;
parameter N = 4;
reg [2**N-1:0] D = 1'd0;
wire [N-1:0] Q;
integer i;
integer p = 2**N;
priority_encoder dut(D, Q);
initial begin
	$monitor("D = %b, Q = %b", D, Q);
	$dumpfile("priority.vcd");
	$dumpvars(0, D, Q);
	repeat(20)
	#2 D = D + 2'd1;
	#2 $finish;
end
endmodule

priority.vcd
$date
	Fri Mar 15 15:58:58 2024
$end
$version
	Icarus Verilog
$end
$timescale
	1ps
$end
$scope module tb $end
$var reg 16 ! D [15:0] $end
$upscope $end
$scope module tb $end
$var wire 4 " Q [3:0] $end
$upscope $end
$enddefinitions $end
#0
$dumpvars
bx "
b0 !
$end
#20000
b0 "
b1 !
#40000
b1 "
b10 !
#60000
b1 "
b11 !
#80000
b10 "
b100 !
#100000
b10 "
b101 !
#120000
b10 "
b110 !
#140000
b10 "
b111 !
#160000
b11 "
b1000 !
#180000
b11 "
b1001 !
#200000
b11 "
b1010 !
#220000
b11 "
b1011 !
#240000
b11 "
b1100 !
#260000
b11 "
b1101 !
#280000
b11 "
b1110 !
#300000
b11 "
b1111 !
#320000
b100 "
b10000 !
#340000
b100 "
b10001 !
#360000
b100 "
b10010 !
#380000
b100 "
b10011 !
#400000
b100 "
b10100 !
