up_3.v
module up_counter3(clk, R, L, I, Q);
input clk;
input R, L;
input [2:0] I;
output reg [2:0] Q;
always @(posedge clk or posedge L) begin
	if (R == 0)
		Q <= 0;
	else if (L)
		Q <= I;
	else
		Q <= Q + 3'b001;
end
endmodule

up_3_tb.v
`timescale 10ns/1ps
module tb;
reg clk;
reg R;
reg L;
reg [2:0] I;
wire [2:0] Q;
up_counter3 dut(clk, R, L, I, Q); 
initial begin
	I = 3'b001;
	L = 1'b1;
	clk = 1'b0;
	R = 1'b1;
	$monitor("clk = %b, I = %b, R = %b, L = %b,  Q= %b", clk, I, R, L, Q);
	$dumpfile("up.vcd");
	$dumpvars(0, clk, I, R, L, Q);
	#1 L = 1'b0;
	repeat(20)
	#2 clk = ~clk;
end
endmodule

up.vcd
$date
	Fri Mar 15 18:29:06 2024
$end
$version
	Icarus Verilog
$end
$timescale
	1ps
$end
$scope module tb $end
$var reg 1 ! clk $end
$upscope $end
$scope module tb $end
$var reg 3 " I [2:0] $end
$upscope $end
$scope module tb $end
$var reg 1 # R $end
$upscope $end
$scope module tb $end
$var reg 1 $ L $end
$upscope $end
$scope module tb $end
$var wire 3 % Q [2:0] $end
$upscope $end
$enddefinitions $end
#0
$dumpvars
b1 %
1$
1#
b1 "
0!
$end
#10000
0$
#30000
b10 %
1!
#50000
0!
#70000
b11 %
1!
#90000
0!
#110000
b100 %
1!
#130000
0!
#150000
b101 %
1!
#170000
0!
#190000
b110 %
1!
#210000
0!
#230000
b111 %
1!
#250000
0!
#270000
b0 %
1!
#290000
0!
#310000
b1 %
1!
#330000
0!
#350000
b10 %
1!
#370000
0!
#390000
b11 %
1!
